sphinxcontrib_seqdiag-3.0.0-py3.10-nspkg.pth
sphinxcontrib/seqdiag.py
sphinxcontrib_seqdiag-3.0.0.dist-info/AUTHORS
sphinxcontrib_seqdiag-3.0.0.dist-info/LICENSE
sphinxcontrib_seqdiag-3.0.0.dist-info/METADATA
sphinxcontrib_seqdiag-3.0.0.dist-info/WHEEL
sphinxcontrib_seqdiag-3.0.0.dist-info/namespace_packages.txt
sphinxcontrib_seqdiag-3.0.0.dist-info/top_level.txt
sphinxcontrib_seqdiag-3.0.0.dist-info/RECORD
